ffsend.py
ffsend-0.1.3.dist-info/LICENSE
ffsend-0.1.3.dist-info/METADATA
ffsend-0.1.3.dist-info/WHEEL
ffsend-0.1.3.dist-info/entry_points.txt
ffsend-0.1.3.dist-info/top_level.txt
ffsend-0.1.3.dist-info/RECORD
