Metadata-Version: 2.1
Name: ffsend
Version: 0.1.3
Summary: A Firefox Send client.
Home-page: https://github.com/nneonneo/ffsend
Author: Robert Xiao
Author-email: robert.bo.xiao@gmail.com
License: MPL 2.0
Platform: UNKNOWN
Classifier: License :: OSI Approved :: Mozilla Public License 2.0 (MPL 2.0)
Classifier: Development Status :: 4 - Beta
Classifier: Operating System :: OS Independent
Classifier: Programming Language :: Python :: 2
Classifier: Programming Language :: Python :: 2.7
Classifier: Programming Language :: Python :: 3
Classifier: Programming Language :: Python :: 3.6
Classifier: Programming Language :: Python :: 3.7
Classifier: Programming Language :: Python :: 3.8
Classifier: Topic :: Utilities
Classifier: Topic :: Communications :: File Sharing
Requires-Dist: clint
Requires-Dist: pycryptodome
Requires-Dist: requests
